<?xml version="1.0" encoding="UTF-8"?>
<movies xmlns:xsi="http://www.w3.org/2001/XMLSchema-instance" xsi:noNamespaceSchemaLocation="ex1.xsd">
    <movie>
        <title>Interstellar</title>
        <director>Christopher Nolan</director>
        <actors>
            <actor>
                <name>Matthew McConaughey</name>
            </actor>
            <actor>
                <name>Anne Hathaway</name>
            </actor>
            <actor>
                <name>Jessica Chastain</name>
            </actor>
        </actors>
        <year>2014</year>
        <synopsis>A team of explorers travel through a wormhole in space in an attempt to ensure humanity's survival.</synopsis>
        <halls>
            <hall id="1">
                <chairType>mesh fabric</chairType>
                <capacity>140</capacity>
            </hall>
            <hall id="2">
                <chairType>leather arm chair</chairType>
                <capacity>95</capacity>
            </hall>
        </halls>
        <schedules>
            <schedule>
                <date>2026-04-02</date>
                <hours>20:15</hours>
                <day>Thursday</day>
            </schedule>
            <schedule>
                <date>2026-04-04</date>
                <hours>17:30</hours>
                <day>Saturday</day>
            </schedule>
        </schedules>
        <genre>action</genre>
    </movie>
    <movie>
        <title>The Matrix</title>
        <director>Lana Wachowski</director>
        <actors>
            <actor>
                <name>Keanu Reeves</name>
            </actor>
            <actor>
                <name>Laurence Fishburne</name>
            </actor>
            <actor>
                <name>Carrie-Anne Moss</name>
            </actor>
        </actors>
        <year>1999</year>
        <synopsis>A hacker discovers the nature of reality and joins a rebellion against the machines controlling humanity.</synopsis>
        <halls>
            <hall id="3">
                <chairType>leather arm chair</chairType>
                <capacity>130</capacity>
            </hall>
        </halls>
        <schedules>
            <schedule>
                <date>2026-04-03</date>
                <hours>19:45</hours>
                <day>Friday</day>
            </schedule>
            <schedule>
                <date>2026-04-05</date>
                <hours>16:00</hours>
                <day>Sunday</day>
            </schedule>
        </schedules>
        <genre>action</genre>
    </movie>
</movies>
